openverse/__init__.py
openverse/make.py
openverse/utils.py
openverse_sdk-0.0.3.dist-info/licenses/LICENSE
openverse_sdk-0.0.3.dist-info/METADATA
openverse_sdk-0.0.3.dist-info/WHEEL
openverse_sdk-0.0.3.dist-info/top_level.txt
openverse_sdk-0.0.3.dist-info/RECORD
