Metadata-Version: 2.4
Name: openverse-sdk
Version: 0.0.3
Summary: Openverse SDK for loading and caching text-based game environments.
Author: Bobby Cheng, Kevin Wang, Yunfei Xie
License: MIT
Project-URL: Homepage, https://github.com/openverse-ai/openverse-sdk
Project-URL: Bug Tracker, https://github.com/openverse-ai/openverse-sdk/issues
Project-URL: Documentation, https://docs.openverse.ai (coming soon)
Classifier: Development Status :: 4 - Beta
Classifier: Intended Audience :: Developers
Classifier: License :: OSI Approved :: MIT License
Classifier: Programming Language :: Python :: 3
Classifier: Topic :: Software Development :: Libraries :: Python Modules
Classifier: Topic :: Games/Entertainment
Requires-Python: >=3.8
License-File: LICENSE
Requires-Dist: textarena>=0.7.3
Dynamic: license-file
